[
	{
		"text": "Du kommst aus dem Gefängnis frei! Behalte diese Karte, bis du sie benötigst oder verkaufst.",
		"action": {
			"type": "unjail"
		}
	},
	{
		"text": "Gehe in das Gefängnis! Begib dich direkt dorthin. Gehe nicht über Los. Ziehe nicht M 200 ein.",
		"action": {
			"type": "jail"
		}
	},
	{
		"text": "Rücke vor bis auf Los. (Ziehe M 200 ein).",
		"action": {
			"type": "move",
			"target": "Los"
		}
	},
	{
		"text": "Zahle Schulgeld: M 50.",
		"action": {
			"type": "money",
			"amount": -50
		}
	},
	{
		"text": "Du erbst M 100.",
		"action": {
			"type": "money",
			"amount": 100
		}
	},
	{
		"text": "Urlaubsgeld! Du erhältst M 100.",
		"action": {
			"type": "money",
			"amount": 100
		}
	},
	{
		"text": "Einkommensteuerrückzahlung. Du erhältst M 20.",
		"action": {
			"type": "money",
			"amount": 20
		}
	},
	{
		"text": "Zweiter Platz im Schönheitswettbewerb. Du erhältst M 10.",
		"action": {
			"type": "money",
			"amount": 10
		}
	},
	{
		"text": "Deine Lebensversicherung wird fällig. Du erhältst M 100.",
		"action": {
			"type": "money",
			"amount": 100
		}
	},
	{
		"text": "Du hast Geburtstag! Jeder Spieler schenkt dir M 10.",
		"action": {
			"type": "moneyplayer",
			"amount": 10
		}
	},
	{
		"text": "Arztkosten. Zahle M 50.",
		"action": {
			"type": "money",
			"amount": -50
		}
	},
	{
		"text": "Aus Lagerverkäufen erhältst du M 50.",
		"action": {
			"type": "money",
			"amount": 50
		}
	},
	{
		"text": "Krankenhausgebühren. Du zahlst M 100.",
		"action": {
			"type": "money",
			"amount": -100
		}
	},
	{
		"text": "Du erhältst eine Beratungsgebühr von M 25.",
		"action": {
			"type": "money",
			"amount": 25
		}
	},
	{
		"text": "Bankirrtum zu deinen Gunsten. Ziehe M 200 ein.",
		"action": {
			"type": "money",
			"amount": 200
		}
	},
	{
		"text": "Kosten für Strassenausbesserungen. Zahle: M 40 pro Haus, M 115 pro Hotel.",
		"action": {
			"type": "moneybuildings",
			"house": 40,
			"hotel": 115
		}
	}
]